acid/__init__.py
acid/app.py
acid/board.py
acid/conf.py
acid/decorators.py
acid/engines.py
acid/game.py
acid/geometry.py
acid_chess-0.1.0rc1.dist-info/LICENSE
acid_chess-0.1.0rc1.dist-info/METADATA
acid_chess-0.1.0rc1.dist-info/WHEEL
acid_chess-0.1.0rc1.dist-info/entry_points.txt
acid_chess-0.1.0rc1.dist-info/top_level.txt
acid_chess-0.1.0rc1.dist-info/RECORD
