Metadata-Version: 2.1
Name: acid-chess
Version: 0.1.0rc1
Summary: The Chess Computer for nerds, by nerds.
Author-email: Bernhard Janetzki <boerni@gmail.com>
Project-URL: Homepage, https://github.com/ierror/acid-chess
Project-URL: Bug Tracker, https://github.com/ierror/acid-chess/issues
Keywords: feed,reader,tutorial
Classifier: Programming Language :: Python :: 3
Classifier: License :: OSI Approved :: MIT License
Classifier: Operating System :: OS Independent
Requires-Python: >=3.9
License-File: LICENSE
